{
  "meta": {
    "trade_date": "2026-05-12",
    "generated_at_kst": "2026-05-12 09:55:39",
    "mode": "closing",
    "session_state": "",
    "leader_count": 15,
    "sector_count": 8,
    "market_bias": "반도체 중심 강세 / 상위섹터 점수 63.5",
    "filtered_etf": "ETF 제외 적용",
    "source_status": "score_leaders_from_market_raw_real",
    "config": {
      "leader_count": 20,
      "min_trading_value_okrw": 1000.0,
      "min_change_pct": 1.0,
      "top_sector_count": 8,
      "per_sector_max": 3,
      "weights": {
        "trading_value": 65,
        "change_pct": 30,
        "volume": 5
      }
    }
  },
  "top_sectors": [
    {
      "sector": "반도체",
      "score": 63.5,
      "leaders": 3,
      "avg_change_pct": 5.96
    },
    {
      "sector": "자동차",
      "score": 53.6,
      "leaders": 3,
      "avg_change_pct": 15.91
    },
    {
      "sector": "전자",
      "score": 52.1,
      "leaders": 1,
      "avg_change_pct": 22.4
    },
    {
      "sector": "로봇",
      "score": 47.2,
      "leaders": 3,
      "avg_change_pct": 14.03
    },
    {
      "sector": "통신",
      "score": 46.8,
      "leaders": 1,
      "avg_change_pct": 8.05
    },
    {
      "sector": "전력",
      "score": 30.2,
      "leaders": 1,
      "avg_change_pct": 15.93
    },
    {
      "sector": "원전",
      "score": 30.0,
      "leaders": 2,
      "avg_change_pct": 7.55
    },
    {
      "sector": "조선",
      "score": 18.0,
      "leaders": 1,
      "avg_change_pct": 4.09
    }
  ],
  "leaders": [
    {
      "code": "000660",
      "name": "SK하이닉스",
      "market": "KOSPI",
      "price": 1948000,
      "change_value": 0,
      "change_pct": 3.62,
      "volume": 1876015,
      "trading_value_okrw": 36544.0,
      "sector1": "반도체",
      "sector2": "",
      "sector": "반도체",
      "score": 68.9,
      "rank": 1
    },
    {
      "code": "012200",
      "name": "계양전기",
      "market": "KOSPI",
      "price": 10990,
      "change_value": 0,
      "change_pct": 29.91,
      "volume": 11734743,
      "trading_value_okrw": 1289.0,
      "sector1": "자동차",
      "sector2": "",
      "sector": "자동차",
      "score": 34.2,
      "rank": 2
    },
    {
      "code": "066570",
      "name": "LG전자",
      "market": "KOSPI",
      "price": 191800,
      "change_value": 0,
      "change_pct": 22.4,
      "volume": 3276702,
      "trading_value_okrw": 6284.0,
      "sector1": "전자",
      "sector2": "",
      "sector": "전자",
      "score": 34.1,
      "rank": 3
    },
    {
      "code": "010170",
      "name": "대한광통신",
      "market": "KOSDAQ",
      "price": 30200,
      "change_value": 0,
      "change_pct": 8.05,
      "volume": 29226780,
      "trading_value_okrw": 8826.0,
      "sector1": "통신",
      "sector2": "",
      "sector": "통신",
      "score": 28.8,
      "rank": 4
    },
    {
      "code": "319400",
      "name": "현대무벡스",
      "market": "KOSDAQ",
      "price": 44800,
      "change_value": 0,
      "change_pct": 15.76,
      "volume": 7536452,
      "trading_value_okrw": 3376.0,
      "sector1": "로봇",
      "sector2": "",
      "sector": "로봇",
      "score": 23.1,
      "rank": 5
    },
    {
      "code": "005380",
      "name": "현대차",
      "market": "KOSPI",
      "price": 689000,
      "change_value": 0,
      "change_pct": 6.66,
      "volume": 1302369,
      "trading_value_okrw": 8973.0,
      "sector1": "자동차",
      "sector2": "",
      "sector": "자동차",
      "score": 22.9,
      "rank": 6
    },
    {
      "code": "009150",
      "name": "삼성전기",
      "market": "KOSPI",
      "price": 994500,
      "change_value": 0,
      "change_pct": 10.5,
      "volume": 651005,
      "trading_value_okrw": 6474.0,
      "sector1": "반도체",
      "sector2": "",
      "sector": "반도체",
      "score": 22.1,
      "rank": 7
    },
    {
      "code": "007610",
      "name": "선도전기",
      "market": "KOSPI",
      "price": 14920,
      "change_value": 0,
      "change_pct": 15.93,
      "volume": 10170297,
      "trading_value_okrw": 1517.0,
      "sector1": "전력",
      "sector2": "",
      "sector": "전력",
      "score": 20.4,
      "rank": 8
    },
    {
      "code": "090710",
      "name": "휴림로봇",
      "market": "KOSDAQ",
      "price": 13590,
      "change_value": 0,
      "change_pct": 10.22,
      "volume": 23774211,
      "trading_value_okrw": 3230.0,
      "sector1": "로봇",
      "sector2": "",
      "sector": "로봇",
      "score": 20.0,
      "rank": 9
    },
    {
      "code": "348340",
      "name": "뉴로메카",
      "market": "KOSDAQ",
      "price": 77900,
      "change_value": 0,
      "change_pct": 16.1,
      "volume": 2000688,
      "trading_value_okrw": 1558.0,
      "sector1": "로봇",
      "sector2": "",
      "sector": "로봇",
      "score": 19.2,
      "rank": 10
    },
    {
      "code": "032820",
      "name": "우리기술",
      "market": "KOSDAQ",
      "price": 21700,
      "change_value": 0,
      "change_pct": 12.44,
      "volume": 8724820,
      "trading_value_okrw": 1893.0,
      "sector1": "원전",
      "sector2": "",
      "sector": "원전",
      "score": 17.3,
      "rank": 11
    },
    {
      "code": "086280",
      "name": "현대글로비스",
      "market": "KOSPI",
      "price": 279000,
      "change_value": 0,
      "change_pct": 11.16,
      "volume": 489570,
      "trading_value_okrw": 1365.0,
      "sector1": "자동차",
      "sector2": "",
      "sector": "자동차",
      "score": 13.7,
      "rank": 12
    },
    {
      "code": "042700",
      "name": "한미반도체",
      "market": "KOSPI",
      "price": 415000,
      "change_value": 0,
      "change_pct": 3.75,
      "volume": 733168,
      "trading_value_okrw": 3042.0,
      "sector1": "반도체",
      "sector2": "",
      "sector": "반도체",
      "score": 9.3,
      "rank": 13
    },
    {
      "code": "329180",
      "name": "HD현대중공업",
      "market": "KOSPI",
      "price": 713000,
      "change_value": 0,
      "change_pct": 4.09,
      "volume": 259095,
      "trading_value_okrw": 1847.0,
      "sector1": "조선",
      "sector2": "",
      "sector": "조선",
      "score": 7.4,
      "rank": 14
    },
    {
      "code": "034020",
      "name": "두산에너빌리티",
      "market": "KOSPI",
      "price": 131400,
      "change_value": 0,
      "change_pct": 2.66,
      "volume": 1773883,
      "trading_value_okrw": 2330.0,
      "sector1": "원전",
      "sector2": "",
      "sector": "원전",
      "score": 7.1,
      "rank": 15
    }
  ]
}