{
  "meta": {
    "trade_date": "2026-06-23",
    "generated_at_kst": "2026-06-23 10:11:30",
    "mode": "closing",
    "session_state": "",
    "leader_count": 9,
    "sector_count": 5,
    "market_bias": "지주사 중심 강세 / 상위섹터 점수 40.6",
    "filtered_etf": "ETF 제외 적용",
    "source_status": "score_leaders_from_market_raw_real",
    "config": {
      "leader_count": 20,
      "min_trading_value_okrw": 1000.0,
      "min_change_pct": 1.0,
      "top_sector_count": 8,
      "per_sector_max": 3,
      "weights": {
        "trading_value": 65,
        "change_pct": 30,
        "volume": 5
      }
    }
  },
  "top_sectors": [
    {
      "sector": "지주사",
      "score": 40.6,
      "leaders": 3,
      "avg_change_pct": 5.21
    },
    {
      "sector": "전력",
      "score": 26.9,
      "leaders": 3,
      "avg_change_pct": 4.99
    },
    {
      "sector": "바이오",
      "score": 20.4,
      "leaders": 1,
      "avg_change_pct": 23.99
    },
    {
      "sector": "반도체",
      "score": 15.7,
      "leaders": 1,
      "avg_change_pct": 15.12
    },
    {
      "sector": "금융",
      "score": 11.3,
      "leaders": 1,
      "avg_change_pct": 5.77
    }
  ],
  "leaders": [
    {
      "code": "402340",
      "name": "SK스퀘어",
      "market": "KOSPI",
      "price": 2080000,
      "change_value": 0,
      "change_pct": 5.58,
      "volume": 951678,
      "trading_value_okrw": 19794.0,
      "sector1": "지주사",
      "sector2": "",
      "sector": "지주사",
      "score": 25.1,
      "rank": 1
    },
    {
      "code": "067290",
      "name": "JW신약",
      "market": "KOSDAQ",
      "price": 3385,
      "change_value": 0,
      "change_pct": 23.99,
      "volume": 33660534,
      "trading_value_okrw": 1139.0,
      "sector1": "바이오",
      "sector2": "",
      "sector": "바이오",
      "score": 11.6,
      "rank": 2
    },
    {
      "code": "006340",
      "name": "대원전선",
      "market": "KOSPI",
      "price": 11220,
      "change_value": 0,
      "change_pct": 8.3,
      "volume": 17167466,
      "trading_value_okrw": 1926.0,
      "sector1": "전력",
      "sector2": "",
      "sector": "전력",
      "score": 6.7,
      "rank": 3
    },
    {
      "code": "320000",
      "name": "한울반도체",
      "market": "KOSDAQ",
      "price": 26650,
      "change_value": 0,
      "change_pct": 15.12,
      "volume": 5642014,
      "trading_value_okrw": 1503.0,
      "sector1": "반도체",
      "sector2": "",
      "sector": "반도체",
      "score": 5.9,
      "rank": 4
    },
    {
      "code": "034730",
      "name": "SK",
      "market": "KOSPI",
      "price": 789000,
      "change_value": 0,
      "change_pct": 8.08,
      "volume": 334137,
      "trading_value_okrw": 2636.0,
      "sector1": "지주사",
      "sector2": "",
      "sector": "지주사",
      "score": 5.0,
      "rank": 5
    },
    {
      "code": "010120",
      "name": "LS ELECTRIC",
      "market": "KOSPI",
      "price": 254500,
      "change_value": 0,
      "change_pct": 3.88,
      "volume": 740808,
      "trading_value_okrw": 1885.0,
      "sector1": "전력",
      "sector2": "",
      "sector": "전력",
      "score": 3.2,
      "rank": 6
    },
    {
      "code": "032830",
      "name": "삼성생명",
      "market": "KOSPI",
      "price": 476500,
      "change_value": 0,
      "change_pct": 5.77,
      "volume": 228593,
      "trading_value_okrw": 1089.0,
      "sector1": "금융",
      "sector2": "",
      "sector": "금융",
      "score": 2.6,
      "rank": 7
    },
    {
      "code": "298040",
      "name": "효성중공업",
      "market": "KOSPI",
      "price": 3941000,
      "change_value": 0,
      "change_pct": 2.79,
      "volume": 35069,
      "trading_value_okrw": 1382.0,
      "sector1": "전력",
      "sector2": "",
      "sector": "전력",
      "score": 2.3,
      "rank": 8
    },
    {
      "code": "000150",
      "name": "두산",
      "market": "KOSPI",
      "price": 1663000,
      "change_value": 0,
      "change_pct": 1.96,
      "volume": 61530,
      "trading_value_okrw": 1023.0,
      "sector1": "지주사",
      "sector2": "",
      "sector": "지주사",
      "score": 1.7,
      "rank": 9
    }
  ]
}