{
  "meta": {
    "trade_date": "2026-04-30",
    "generated_at_kst": "2026-04-30 14:36:39",
    "mode": "closing",
    "session_state": "",
    "leader_count": 20,
    "sector_count": 8,
    "market_bias": "전력 중심 강세 / 상위섹터 점수 72.3",
    "filtered_etf": "ETF 제외 적용",
    "source_status": "score_leaders_from_market_raw_real",
    "config": {
      "leader_count": 20,
      "min_trading_value_okrw": 1000.0,
      "min_change_pct": 1.0,
      "top_sector_count": 8,
      "per_sector_max": 3,
      "weights": {
        "trading_value": 65,
        "change_pct": 30,
        "volume": 5
      }
    }
  },
  "top_sectors": [
    {
      "sector": "전력",
      "score": 72.3,
      "leaders": 3,
      "avg_change_pct": 17.28
    },
    {
      "sector": "반도체",
      "score": 49.4,
      "leaders": 3,
      "avg_change_pct": 10.55
    },
    {
      "sector": "철강",
      "score": 48.4,
      "leaders": 2,
      "avg_change_pct": 25.59
    },
    {
      "sector": "에너지",
      "score": 44.3,
      "leaders": 3,
      "avg_change_pct": 6.69
    },
    {
      "sector": "화학",
      "score": 40.4,
      "leaders": 1,
      "avg_change_pct": 14.83
    },
    {
      "sector": "전자",
      "score": 32.8,
      "leaders": 1,
      "avg_change_pct": 3.39
    },
    {
      "sector": "통신",
      "score": 32.6,
      "leaders": 2,
      "avg_change_pct": 6.12
    },
    {
      "sector": "지주사",
      "score": 24.4,
      "leaders": 1,
      "avg_change_pct": 2.17
    }
  ],
  "leaders": [
    {
      "code": "001440",
      "name": "대한전선",
      "market": "KOSPI",
      "price": 57300,
      "change_value": 0,
      "change_pct": 11.91,
      "volume": 31975387,
      "trading_value_okrw": 18321.0,
      "sector1": "전력",
      "sector2": "",
      "sector": "전력",
      "score": 48.1,
      "rank": 1
    },
    {
      "code": "006340",
      "name": "대원전선",
      "market": "KOSPI",
      "price": 15710,
      "change_value": 0,
      "change_pct": 20.02,
      "volume": 76743609,
      "trading_value_okrw": 12056.0,
      "sector1": "전력",
      "sector2": "",
      "sector": "전력",
      "score": 47.5,
      "rank": 2
    },
    {
      "code": "024840",
      "name": "KBI메탈",
      "market": "KOSDAQ",
      "price": 5100,
      "change_value": 0,
      "change_pct": 29.94,
      "volume": 39111062,
      "trading_value_okrw": 1994.0,
      "sector1": "철강",
      "sector2": "",
      "sector": "철강",
      "score": 36.2,
      "rank": 3
    },
    {
      "code": "062040",
      "name": "산일전기",
      "market": "KOSPI",
      "price": 265000,
      "change_value": 0,
      "change_pct": 19.91,
      "volume": 2261211,
      "trading_value_okrw": 5992.0,
      "sector1": "전력",
      "sector2": "",
      "sector": "전력",
      "score": 31.2,
      "rank": 4
    },
    {
      "code": "125020",
      "name": "티씨머티리얼즈",
      "market": "KOSDAQ",
      "price": 8850,
      "change_value": 0,
      "change_pct": 21.23,
      "volume": 22742507,
      "trading_value_okrw": 2012.0,
      "sector1": "철강",
      "sector2": "",
      "sector": "철강",
      "score": 26.5,
      "rank": 5
    },
    {
      "code": "025860",
      "name": "남해화학",
      "market": "KOSPI",
      "price": 10840,
      "change_value": 0,
      "change_pct": 14.83,
      "volume": 36414331,
      "trading_value_okrw": 3947.0,
      "sector1": "화학",
      "sector2": "",
      "sector": "화학",
      "score": 24.6,
      "rank": 6
    },
    {
      "code": "042700",
      "name": "한미반도체",
      "market": "KOSPI",
      "price": 373000,
      "change_value": 0,
      "change_pct": 4.34,
      "volume": 2410935,
      "trading_value_okrw": 8992.0,
      "sector1": "반도체",
      "sector2": "",
      "sector": "반도체",
      "score": 21.2,
      "rank": 7
    },
    {
      "code": "046890",
      "name": "서울반도체",
      "market": "KOSDAQ",
      "price": 16330,
      "change_value": 0,
      "change_pct": 14.04,
      "volume": 13181130,
      "trading_value_okrw": 2152.0,
      "sector1": "반도체",
      "sector2": "",
      "sector": "반도체",
      "score": 18.9,
      "rank": 8
    },
    {
      "code": "432720",
      "name": "퀄리타스반도체",
      "market": "KOSDAQ",
      "price": 24750,
      "change_value": 0,
      "change_pct": 13.27,
      "volume": 8882461,
      "trading_value_okrw": 2198.0,
      "sector1": "반도체",
      "sector2": "",
      "sector": "반도체",
      "score": 17.9,
      "rank": 9
    },
    {
      "code": "009830",
      "name": "한화솔루션",
      "market": "KOSPI",
      "price": 50400,
      "change_value": 0,
      "change_pct": 5.11,
      "volume": 11363291,
      "trading_value_okrw": 5727.0,
      "sector1": "에너지",
      "sector2": "",
      "sector": "에너지",
      "score": 16.5,
      "rank": 10
    },
    {
      "code": "066570",
      "name": "LG전자",
      "market": "KOSPI",
      "price": 140400,
      "change_value": 0,
      "change_pct": 3.39,
      "volume": 4257439,
      "trading_value_okrw": 5977.0,
      "sector1": "전자",
      "sector2": "",
      "sector": "전자",
      "score": 14.8,
      "rank": 11
    },
    {
      "code": "322000",
      "name": "HD현대에너지솔루션",
      "market": "KOSPI",
      "price": 234500,
      "change_value": 0,
      "change_pct": 8.82,
      "volume": 1347639,
      "trading_value_okrw": 3160.0,
      "sector1": "에너지",
      "sector2": "",
      "sector": "에너지",
      "score": 14.8,
      "rank": 12
    },
    {
      "code": "050890",
      "name": "쏠리드",
      "market": "KOSDAQ",
      "price": 17160,
      "change_value": 0,
      "change_pct": 6.78,
      "volume": 20137391,
      "trading_value_okrw": 3455.0,
      "sector1": "통신",
      "sector2": "",
      "sector": "통신",
      "score": 14.5,
      "rank": 13
    },
    {
      "code": "024060",
      "name": "흥구석유",
      "market": "KOSDAQ",
      "price": 17980,
      "change_value": 0,
      "change_pct": 6.14,
      "volume": 13355784,
      "trading_value_okrw": 2401.0,
      "sector1": "에너지",
      "sector2": "",
      "sector": "에너지",
      "score": 11.5,
      "rank": 14
    },
    {
      "code": "490470",
      "name": "세미파이브",
      "market": "KOSDAQ",
      "price": 42400,
      "change_value": 0,
      "change_pct": 7.61,
      "volume": 2967617,
      "trading_value_okrw": 1258.0,
      "sector1": "기타",
      "sector2": "",
      "sector": "기타",
      "score": 10.2,
      "rank": 15
    },
    {
      "code": "041910",
      "name": "폴라리스AI파마",
      "market": "KOSDAQ",
      "price": 7640,
      "change_value": 0,
      "change_pct": 7.15,
      "volume": 14435474,
      "trading_value_okrw": 1102.0,
      "sector1": "바이오",
      "sector2": "",
      "sector": "바이오",
      "score": 10.1,
      "rank": 16
    },
    {
      "code": "454910",
      "name": "두산로보틱스",
      "market": "KOSPI",
      "price": 108600,
      "change_value": 0,
      "change_pct": 6.26,
      "volume": 1655364,
      "trading_value_okrw": 1797.0,
      "sector1": "로봇",
      "sector2": "",
      "sector": "로봇",
      "score": 9.7,
      "rank": 17
    },
    {
      "code": "178320",
      "name": "서진시스템",
      "market": "KOSDAQ",
      "price": 59800,
      "change_value": 0,
      "change_pct": 5.47,
      "volume": 3386360,
      "trading_value_okrw": 2025.0,
      "sector1": "통신",
      "sector2": "",
      "sector": "통신",
      "score": 9.5,
      "rank": 18
    },
    {
      "code": "402340",
      "name": "SK스퀘어",
      "market": "KOSPI",
      "price": 848000,
      "change_value": 0,
      "change_pct": 2.17,
      "volume": 438863,
      "trading_value_okrw": 3721.0,
      "sector1": "지주사",
      "sector2": "",
      "sector": "지주사",
      "score": 9.1,
      "rank": 19
    },
    {
      "code": "064350",
      "name": "현대로템",
      "market": "KOSPI",
      "price": 267000,
      "change_value": 0,
      "change_pct": 1.14,
      "volume": 1287582,
      "trading_value_okrw": 3437.0,
      "sector1": "방산",
      "sector2": "",
      "sector": "방산",
      "score": 7.6,
      "rank": 20
    }
  ]
}